{
  "appId": "uz.smartlake.app",
  "appName": "SmartLake",
  "webDir": "dist",
  "server": {
    "androidScheme": "https"
  },
  "android": {
    "buildOptions": {
      "keystorePath": null,
      "keystoreAlias": null
    },
    "allowMixedContent": false,
    "captureInput": true,
    "webContentsDebuggingEnabled": false
  },
  "plugins": {
    "SplashScreen": {
      "launchShowDuration": 2000,
      "backgroundColor": "#0E7C6B",
      "showSpinner": false,
      "androidSplashResourceName": "splash",
      "androidScaleType": "CENTER_CROP"
    },
    "StatusBar": {
      "style": "LIGHT",
      "backgroundColor": "#0E7C6B"
    }
  }
}
